wammodels/OPTIMIZACION_NEW.r
wammodels/__init__.py
wammodels/combination.py
wammodels/descomp.py
wammodels/global_func.py
wammodels/optimization.py
wammodels-0.0.11.dist-info/METADATA
wammodels-0.0.11.dist-info/WHEEL
wammodels-0.0.11.dist-info/top_level.txt
wammodels-0.0.11.dist-info/RECORD
