Metadata-Version: 2.1
Name: wammodels
Version: 0.0.11
Summary: library for customization modeling .WA
Author: Felipe Ardila (WorldArd)
Requires-Dist: pandas
Requires-Dist: numpy
Requires-Dist: statsmodels
Requires-Dist: patsy
Requires-Dist: plotly
Requires-Dist: rpy2
